pystk2.cp310-win_amd64.pyd
pystk2-0.1.0.dist-info/METADATA
pystk2-0.1.0.dist-info/WHEEL
pystk2-0.1.0.dist-info/entry_points.txt
pystk2-0.1.0.dist-info/licenses/COPYING
pystk2-0.1.0.dist-info/RECORD
