Metadata-Version: 2.1
Name: pystk2
Version: 0.1.0
Summary: Python bindings for SuperTuxKart
Author-Email: Benjamin Piwowarski <benjamin@piwowarski.fr>
Classifier: Development Status :: 4 - Beta
Classifier: License :: OSI Approved :: MIT License
Classifier: Programming Language :: Python :: 3 :: Only
Classifier: Programming Language :: Python :: 3.8
Classifier: Programming Language :: Python :: 3.9
Classifier: Programming Language :: Python :: 3.10
Classifier: Programming Language :: Python :: 3.11
Requires-Python: >=3.8
Requires-Dist: platformdirs
Requires-Dist: numpy
License-File: COPYING
